semantix/__init__.py
semantix/decorators.py
semantix/inference.py
semantix/llms/__init__.py
semantix/llms/_anthropic.py
semantix/llms/_cohere.py
semantix/llms/_google.py
semantix/llms/_groq.py
semantix/llms/_mistral.py
semantix/llms/_openai.py
semantix/llms/_together.py
semantix/llms/base.py
semantix/tools/__init__.py
semantix/types/__init__.py
semantix/types/media.py
semantix/types/prompt.py
semantix/types/semantic.py
semantix/utils/__init__.py
semantix/utils/helpers.py
semantix/utils/utils.py
semantix-0.1.7.dist-info/LICENSE
semantix-0.1.7.dist-info/METADATA
semantix-0.1.7.dist-info/WHEEL
semantix-0.1.7.dist-info/RECORD
