Metadata-Version: 2.1
Name: semantix
Version: 0.1.7
Summary: Give Superpowers to your python function. GenAI Application development made easy.
Home-page: https://github.com/chandralegend/semantix
License: MIT
Keywords: no-prompt,llm,meaning-typed,autoprompt
Author: Chandra Irugalbandara
Author-email: irugalbandara@ascii.ai
Maintainer: Chandra Irugalbandara
Maintainer-email: irugalbandara@ascii.ai
Requires-Python: >=3.8,<4.0
Classifier: License :: OSI Approved :: MIT License
Classifier: Programming Language :: Python :: 3
Classifier: Programming Language :: Python :: 3.8
Classifier: Programming Language :: Python :: 3.9
Classifier: Programming Language :: Python :: 3.10
Classifier: Programming Language :: Python :: 3.11
Classifier: Programming Language :: Python :: 3.12
Classifier: Programming Language :: Python :: 3.13
Provides-Extra: anthropic
Provides-Extra: cohere
Provides-Extra: groq
Provides-Extra: image
Provides-Extra: mistralai
Provides-Extra: openai
Provides-Extra: together
Provides-Extra: video
Requires-Dist: anthropic (>=0.34.2,<0.35.0) ; extra == "anthropic"
Requires-Dist: cohere (>=5.9.2,<6.0.0) ; extra == "cohere"
Requires-Dist: groq (>=0.11.0,<0.12.0) ; extra == "groq"
Requires-Dist: loguru (>=0.7.2,<0.8.0)
Requires-Dist: mistralai (>=1.0.3,<2.0.0) ; extra == "mistralai"
Requires-Dist: openai (>=1.44.0,<2.0.0) ; extra == "openai"
Requires-Dist: together (>=1.2.12,<2.0.0) ; extra == "together"
Project-URL: Documentation, https://chandralegend.github.io/semantix/
Project-URL: Repository, https://github.com/chandralegend/semantix
